unicat_esolang/__init__.py
unicat_esolang/unicat.py
unicat_esolang-0.1.4.dist-info/LICENSE.txt
unicat_esolang-0.1.4.dist-info/METADATA
unicat_esolang-0.1.4.dist-info/WHEEL
unicat_esolang-0.1.4.dist-info/entry_points.txt
unicat_esolang-0.1.4.dist-info/RECORD
