Metadata-Version: 2.1
Name: unicat-esolang
Version: 0.1.4
Summary: Python 3 Port of Unicat Esoteric Language. This is a fork of https://github.com/gemdude46/unicat
Home-page: https://github.com/rzuckerm/unicat-esolang
License: LICENSE.txt
Author: rzuckerm
Requires-Python: >=3.8,<4.0
Classifier: Development Status :: 3 - Alpha
Classifier: License :: OSI Approved :: MIT License
Classifier: License :: Other/Proprietary License
Classifier: Operating System :: OS Independent
Classifier: Programming Language :: Python :: 3
Classifier: Programming Language :: Python :: 3.8
Classifier: Programming Language :: Python :: 3.9
Classifier: Programming Language :: Python :: 3.10
Classifier: Programming Language :: Python :: 3.11
Project-URL: Bug Tracker, https://github.com/rzuckerm/unicat-esolang/issues
